{
    "source_url": "https://www.constructionequipmentguide.com/charts/charts/truck-cranes/grove/td522/12947",
    "source_url_id": "12947",
    "source_url_model": "td522",
    "source_url_make": "grove",
    "source_url_category": "truck-cranes",
    "source_date_scraped": "2023-09-13 17:49:30.916127",
    "equipment_category": "Truck Cranes",
    "equipment_make": "Grove",
    "equipment_model": "TD522",
    "equipment_spec": {
        "Boom": {
            "Max Elevating Angle": "75  \t\u00b0",
            "Max Height @ Max Raise Angle - no jib": "70 ft (21 m)",
            "Max Lift Capacity": "44000 lbs (19,958 kg)",
            "Max Working Radius": "65 ft (20 m)",
            "Min Height @ Max Raise Angle": "28 ft (9 m)",
            "Min Working Radius": "10 ft (3 m)",
            "Number of Sections": "3",
            "Swing Speed": "3 rpm"
        },
        "CARRIER ENGINE": {
            "Displacement": "555 cu in (0 m)",
            "Gross Power": "225 hp (168 kw)",
            "Make": "Grove",
            "Max Torque": "361 lbs/ft",
            "Model": "VT225",
            "Net Power": "182.5 hp (136 kw)",
            "Number of cylinders": "8",
            "Power Measured @": "3000 rpm",
            "Torque Measured @": "1900 rpm"
        },
        "Dimensions": {
            "Carrier Length": "27.7 ft (8 m)",
            "Ground Clearance": "0.8 ft (0 m)",
            "Transport Height": "11.8 ft (3 m)",
            "Transport Length": "35.7 ft (11 m)",
            "Transport Width": "8 ft (2 m)",
            "Upper Structure Tail Swing Radius": "9.8 ft (3 m)",
            "Width w/ Outriggers Extended": "19 ft (6 m)"
        },
        "Operating Specifications": {
            "Alternator Supplied Amperage": "90  A",
            "Carrier Cooling System Fluid Capacity": "10.1 gal (38 l)",
            "Carrier Fuel Capacity": "60 gal (227 l)",
            "Number of Axels": "3",
            "Operating Voltage": "24 V V",
            "Operating Weight": "46879 lbs (21,264 kg)",
            "Tire Size": "front 15x22.5 rear 10.00x20-12PR",
            "Upper Structure Hydraulic System Fluid Capacity": "88 gal (333 l)"
        },
        "Transmission": {
            "Max Speed - Forward": "56.1 mph (90 kph)",
            "Number of Forward Gears": "13",
            "Number of Reverse Gears": "3",
            "Transmission Type": "Fuller Roadranger RT6613"
        }
    }
}