{
    "source_url": "https://www.constructionequipmentguide.com/charts/charts/aerial-lifts/snorkel/ab60j/29487",
    "source_url_id": "29487",
    "source_url_model": "ab60j",
    "source_url_make": "snorkel",
    "source_url_category": "aerial-lifts",
    "source_date_scraped": "2023-09-13 14:31:20.780826",
    "equipment_category": "Aerial Lifts",
    "equipment_make": "Snorkel",
    "equipment_model": "AB60J",
    "equipment_spec": {
        "Capacity": {
            "Platform Capacity": "500 lbs (227 kg)"
        },
        "Dimensions": {
            "Boom Type/Size": "AT,J ft (0 m)",
            "Platform Size": "5x2.5 ft (2 m)",
            "Stowed Height": "8..2 ft (2 m)",
            "Stowed Width": "7.9 ft (2 m)"
        },
        "Tires": {
            "Tire Size": "15x19.5"
        },
        "Transmission": {
            "4WD": "Std"
        }
    }
}