{
    "source_url": "https://www.constructionequipmentguide.com/charts/charts/skid-steer-loaders/daewoo/dsl602/30169645",
    "source_url_id": "30169645",
    "source_url_model": "dsl602",
    "source_url_make": "daewoo",
    "source_url_category": "skid-steer-loaders",
    "source_date_scraped": "2023-09-13 16:37:36.360946",
    "equipment_category": "Skid Steer Loaders",
    "equipment_make": "Daewoo",
    "equipment_model": "DSL602",
    "equipment_spec": {
        "Dimensions": {
            "Clearance at Max Lift and Dump": "7.2 ft (2 m)",
            "Ground Clearance": "7.5 in (18 cm)",
            "Height - Top of Cab": "6.4 ft (2 m)",
            "Length w/o Bucket": "7.6 ft (2 m)",
            "Length with Bucket": "9.8 ft (3 m)",
            "Reach at Max Lift and Dump": "20.4 in (51 cm)",
            "Turning Radius from Center - inc bucket": "71.1 in (180 cm)",
            "Turning Radius from Center - machine rear": "57.7 in (145 cm)",
            "Wheelbase": "3.2 ft (1 m)",
            "Width Over Tires": "4.9 ft (1 m)"
        },
        "Engine": {
            "Displacement": "121.8 cu in (0 m)",
            "Engine Model": "4TNE84",
            "Gross Power": "42 hp (31 kw)",
            "Number of Cylinders": "4",
            "Power Measured @": "2800 rpm"
        },
        "Hydraulic System": {
            "Pump Flow Capacity": "11.9 gal/min (42 l/min)"
        },
        "Loader": {
            "Breakout Force": "2888.1 psi",
            "Bucket Capacity": "0.5 cu yds (0 m)",
            "Operating Load Rating": "1300.8 lbs (590 kg)",
            "Tipping Angle": "2910.2  \t\u00b0"
        },
        "Operating Specifications": {
            "Fuel Capacity": "13.9 gal (49 l)",
            "Max Speed": "6.7 mph (10 kph)",
            "Operational Weight": "5412.4 lbs (2,455 kg)",
            "Tire Size": "10 x 16.5"
        }
    }
}