{
    "source_url": "https://www.constructionequipmentguide.com/charts/charts/rough-terrain-cranes/tadano/tr-250m-4/30298",
    "source_url_id": "30298",
    "source_url_model": "tr-250m-4",
    "source_url_make": "tadano",
    "source_url_category": "rough-terrain-cranes",
    "source_date_scraped": "2023-09-13 17:48:58.358483",
    "equipment_category": "Rough Terrain Cranes",
    "equipment_make": "Tadano",
    "equipment_model": "TR-250M-4",
    "equipment_spec": {
        "Boom": {
            "Max Elevating Angle": "83  \t\u00b0",
            "Max Height @ Max Raise Angle - no jib": "93.6 ft (28 m)",
            "Min Height @ Max Raise Angle": "29.6 ft (9 m)",
            "Number of Sections": "4",
            "Swing Speed": "3 rpm"
        },
        "Dimensions": {
            "Carrier/Base Length": "24212.6 ft (7,380 m)",
            "Transport Height": "11.6 ft (3 m)",
            "Transport Length": "35.8 ft (11 m)",
            "Transport Width": "8.6 ft (2 m)",
            "Upper Structure Tail Swing Radius": "10.2 ft (3 m)",
            "Wheelbase": "135.9 in (343 cm)",
            "Width w/ Outriggers Extended": "20.7 ft (6 m)"
        },
        "Engine": {
            "Aspiration": "Water-cooled",
            "Displacement": "460.5 cu in (0 m)",
            "Engine Make": "Mitsubishi",
            "Engine Model": "6D16",
            "Gross Power": "212.1 hp (158 kw)",
            "Max Torque": "470.2 lbs/ft",
            "Number of Cylinders": "6",
            "Power Measured @": "2800 rpm",
            "Torque Measured @": "1800 rpm"
        },
        "Operating Specifications": {
            "Fuel Capacity": "79.3 gal (299 l)",
            "Hydraulic System Fluid Capacity": "107.6 gal (405 l)",
            "Operating Voltage": "24 V V",
            "Operating Weight": "57981.6 lbs (26,300 kg)",
            "Tire Size": "16.00-25-28PR"
        },
        "Transmission": {
            "Max Speed - Forward": "30.5 mph (48 kph)",
            "Number of Forward Gears": "3",
            "Number of Reverse Gears": "1",
            "Transmission Type": "Powershift"
        }
    }
}