{
    "source_url": "https://www.constructionequipmentguide.com/charts/charts/smooth-drum-rollers/caterpillar/cb434b/30671853",
    "source_url_id": "30671853",
    "source_url_model": "cb434b",
    "source_url_make": "caterpillar",
    "source_url_category": "smooth-drum-rollers",
    "source_date_scraped": "2023-09-13 17:41:41.376108",
    "equipment_category": "Smooth Drum Rollers",
    "equipment_make": "Caterpillar",
    "equipment_model": "CB434B",
    "equipment_spec": {
        "Dimensions": {
            "Turning Radius - Inside": "134 in (340 cm)"
        },
        "Drum": {
            "Drum Width": "56 in (142 cm)",
            "Vibration Frequency": "2900 hz (174,000 vpm)"
        },
        "Engine": {
            "Make": "Caterpillar"
        },
        "Operating Specifications": {
            "Operating Width": "63.5 in (160 cm)"
        }
    }
}