{
    "source_url": "https://www.constructionequipmentguide.com/charts/charts/padfoot-compactors/ammann/asc90pd/30753852",
    "source_url_id": "30753852",
    "source_url_model": "asc90pd",
    "source_url_make": "ammann",
    "source_url_category": "padfoot-compactors",
    "source_date_scraped": "2023-09-13 17:39:23.646379",
    "equipment_category": "Padfoot Compactors",
    "equipment_make": "Ammann",
    "equipment_model": "ASC90PD",
    "equipment_spec": {
        "Dimensions": {
            "Ground Clearance": "15.2 in (38 cm)",
            "Height - Top of Cab": "9.5 ft (3 m)",
            "Overall Length w/o Blade": "17.1 ft (5 m)",
            "Wheelbase": "8.4 in (20 cm)",
            "Width Over Tires": "6.4 ft (2 m)"
        },
        "Drum": {
            "Centrifugal Force - High": "32597.3 lbs (14,786 kg)",
            "Centrifugal Force - Low": "35969.5 lbs (16,315 kg)",
            "Drum Diameter": "48.9 in (122 cm)",
            "Drum Width": "66.2 in (168 cm)",
            "Nominal Amplitude - High": "0.1 in (0 cm)",
            "Nominal Amplitude - Low": "0.1 in (0 cm)",
            "Number of Pads": "104",
            "Pad Height": "3.2 in (8 cm)",
            "Pad Surface Area": "17.7 cu in (0 m)",
            "Vibration Frequency 1": "30 hz (1,800 vpm)",
            "Vibratory Frequency 2": "40 hz (2,400 vpm)"
        },
        "Engine": {
            "Displacement": "274.7 cu in (0 m)",
            "Engine Model": "B4.5-C99",
            "Net Power": "101 hp (75 kw)",
            "Number of Cylinders": "4",
            "Power Measured @": "2200 rpm"
        },
        "Operating Specifications": {
            "Fuel Capacity": "72.7 gal (273 l)",
            "Max Speed": "6.9 mph (10 kph)",
            "Operating Weight": "19323.6 lbs (8,765 kg)"
        },
        "Tires": {
            "Tires": "14.9-24"
        }
    }
}