{
    "source_url": "https://www.constructionequipmentguide.com/charts/charts/off-highway-trucks/komatsu/830e-ac/30754708",
    "source_url_id": "30754708",
    "source_url_model": "830e-ac",
    "source_url_make": "komatsu",
    "source_url_category": "off-highway-trucks",
    "source_date_scraped": "2023-09-13 16:25:08.162830",
    "equipment_category": "Off-Highway Trucks",
    "equipment_make": "Komatsu",
    "equipment_model": "830E-AC",
    "equipment_spec": {
        "Articulating/Rigid": {
            "Articulating/Rigid": "Rigid"
        },
        "Dimensions": {
            "Dump Ground Clearance": "6 ft (2 m)",
            "Dump Height": "44 ft (13 m)",
            "Ground Clearance": "4.2 ft (1 m)",
            "Overall Height": "22.6 ft (7 m)",
            "Overall Length": "46.5 ft (14 m)",
            "Overall Width": "24.1 ft (7 m)",
            "Wheelbase": "20.9 ft (6 m)"
        },
        "DRIVE SYSTEM": {
            "Drive Config": "rwd"
        },
        "Dump": {
            "Load Capacity - heaped": "193 cu yds (148 m)",
            "Load Capacity - Struck": "153 cu yds (117 m)",
            "Lower Time": "27 sec",
            "Raise Time": "25 sec",
            "Rated Payload": "488000 lbs (221,355 kg)"
        },
        "Engine": {
            "Aspiration": "260  A",
            "Engine Model": "SDA16V160",
            "Gross Power": "2360 hp (1,760 kw)",
            "Make": "Komatsu",
            "Model": "SDA16V160",
            "Number of Cylinders": "16",
            "Rated Engine Speed": "250 rpm"
        },
        "Operating Specifications": {
            "Alternator Supplied Amperage": "260  A",
            "Cooling System Fluid Capacity": "150 gal (568 l)",
            "Fuel Capacity": "1200 gal (4,542 l)",
            "Hydraulic System Fluid Capacity": "250 gal (946 l)",
            "Not to Exceed Payload (120%)*": "lbs (0 kg)",
            "Steering System Fluid Capacity": "238 gal (901 l)"
        },
        "Service Refill Capacities": {
            "Brake/Hoist Hydraulic Tank": "488000 gal (1,847,080 l)"
        },
        "Transmission": {
            "Max Speed": "40 mph (64 kph)"
        },
        "Weights": {
            "Empty Weight": "362000 lbs (164,202 kg)",
            "Loaded Weight": "850650 lbs (385,852 kg)",
            "Operating Weight": "850650 lbs (385,852 kg)",
            "Weight Distribution Front - empty": "50%",
            "Weight Distribution Front - loaded": "33%",
            "Weight Distribution Rear - empty": "50%",
            "Weight Distribution Rear - loaded": "67%"
        }
    }
}