{
    "source_url": "https://www.constructionequipmentguide.com/charts/charts/backhoe-loaders/caterpillar/428-ii/30750355",
    "source_url_id": "30750355",
    "source_url_model": "428-ii",
    "source_url_make": "caterpillar",
    "source_url_category": "backhoe-loaders",
    "source_date_scraped": "2023-09-13 14:34:40.893206",
    "equipment_category": "Backhoe Loaders",
    "equipment_make": "Caterpillar",
    "equipment_model": "428 II",
    "equipment_spec": {
        "Backhoe": {
            "Bucket Dig Force": "10438 lbs (4,735 kg)",
            "Bucket Dig Force - Extended": "10258 lbs (4,653 kg)",
            "Dig Depth": "15.6 ft (5 m)",
            "Dig Depth - Extended": "19.7 ft (6 m)",
            "Load Height": "11.5 ft (3 m)",
            "Load Height - Extended": "13.8 ft (4 m)",
            "Reach From Swivel": "17.7 ft (5 m)",
            "Reach From Swivel - Extended": "21.8 ft (6 m)"
        },
        "Dimensions": {
            "Ground Clearance": "1.1 ft (0 m)",
            "Height to Top of Suspended Cab": "9.2 ft (3 m)",
            "Transport Length": "18.7 ft (5 m)",
            "Transport Width": "7.9 ft (2 m)",
            "Wheelbase": "6.9 ft (2 m)"
        },
        "Engine": {
            "Displacement": "235.6 cu in (0 m)",
            "Engine Model": "4.236",
            "Gross Power": "75.1 hp (56 kw)",
            "Net Power": "69.8 hp (51 kw)"
        },
        "Hydraulic System": {
            "Pump Flow Capacity": "28.6 gal/min (106 l/min)",
            "Relief Valve Pressure": "2700 psi"
        },
        "Loader": {
            "Bucket Breakout Force": "8048.2 lbs (3,651 kg)",
            "Bucket Capacity": "1.4 cu yds (1 m)",
            "Bucket Width": "94.4 in (239 cm)",
            "Clearance at Max Dump Height": "8.7 ft (2 m)",
            "Dig Depth": "3.9 in (8 cm)",
            "Lift Capacity": "3836.1 lbs (1,740 kg)",
            "Reach at Max Dump Height": "2.8 ft (1 m)"
        },
        "Operating Specifications": {
            "Operating Weight 2wd": "15747.7 lbs (7,143 kg)",
            "Tire Size Front - 2wd / 4wd": "9-16 10PR / 10.5-20 10PR",
            "Turning Radius": "12.9 ft (4 m)"
        },
        "Tires": {
            "Rear Tires Size": "16.9-28 10 PR"
        },
        "Transmission": {
            "Max Speed": "18.3 mph (29 kph)",
            "Max Speed - Reverse": "18.4 mph (29 kph)",
            "Number of Forward Gears": "4",
            "Number of Reverse Gears": "4"
        }
    }
}