{
    "source_url": "https://www.constructionequipmentguide.com/charts/charts/cab-chassis-trucks/volvo/fl-e-18-tonne-4x2-rigid-2005/30759233",
    "source_url_id": "30759233",
    "source_url_model": "fl-e-18-tonne-4x2-rigid-2005",
    "source_url_make": "volvo",
    "source_url_category": "cab-chassis-trucks",
    "source_date_scraped": "2023-09-13 17:57:29.458932",
    "equipment_category": "Cab / Chassis Trucks",
    "equipment_make": "Volvo",
    "equipment_model": "FL E 18 Tonne 4x2 Rigid (2005)",
    "equipment_spec": {
        "Dimensions": {
            "Height - Top of Cab": "9 ft (3 m)",
            "Number of Rear Axles": "1",
            "Overall Width": "8.3 ft (2 m)",
            "Tire Size": "front: 295/80R22.5, rear: 295/R22.5",
            "Weight Class": "8"
        },
        "Wheelbase Cab Chassis Option 1": {
            "Length from Back of Cab to End of Frame": "176.2 in (447 cm)",
            "Length From Back of Cab to End of Frame": "176.19 in (447 cm)",
            "Length from Center of Rear Axle(s) to End of Frame": "56 in (142 cm)",
            "Length From Center of Rear Axle(s) to End of Frame": "55.91 in (140 cm)",
            "Overall Length": "20.8 ft (6 m)",
            "Total Chassis Weight": "11199.5 lbs (5,080 kg)",
            "Total GVW": "39683.3 lbs (18,000 kg)",
            "Turning Radius": "22.4 ft (7 m)",
            "Wheelbase": "133.9 in (338 cm)"
        },
        "Wheelbase Cab Chassis Option 2": {
            "Length from Back of Cab to End of Frame": "205 in (521 cm)",
            "Length From Back of Cab to End of Frame": "204.93 in (518 cm)",
            "Length from Center of Rear Axle(s) to End of Frame": "61.1 in (155 cm)",
            "Length From Center of Rear Axle(s) to End of Frame": "61.03 in (155 cm)",
            "Overall Length": "23.2 ft (7 m)",
            "Total Chassis Weight": "11331.8 lbs (5,140 kg)",
            "Total GVW": "39683.3 lbs (18,000 kg)",
            "Turning Radius": "25.1 ft (8 m)",
            "Wheelbase": "157.5 in (399 cm)"
        },
        "Wheelbase Cab Chassis Option 3": {
            "Length from Back of Cab to End of Frame": "222.7 in (564 cm)",
            "Length From Back of Cab to End of Frame": "222.64 in (564 cm)",
            "Length From Center of Rear Axle(s) to End of Frame": "66.93 in (168 cm)",
            "Length from Center of Rear Axle(s) to End of Frame": "67 in (170 cm)",
            "Overall Length": "24.7 ft (7 m)",
            "Total Chassis Weight": "11375.9 lbs (5,160 kg)",
            "Total GVW": "39683.3 lbs (18,000 kg)",
            "Turning Radius": "26.6 ft (8 m)",
            "Wheelbase": "169.3 in (429 cm)"
        },
        "Wheelbase Cab Chassis Option 4": {
            "Length From Back of Cab to End of Frame": "241.15 in (612 cm)",
            "Length from Back of Cab to End of Frame": "241.2 in (612 cm)",
            "Length From Center of Rear Axle(s) to End of Frame": "73.63 in (185 cm)",
            "Length from Center of Rear Axle(s) to End of Frame": "73.7 in (185 cm)",
            "Overall Length": "26.2 ft (8 m)",
            "Total Chassis Weight": "11397.9 lbs (5,170 kg)",
            "Total GVW": "39683.3 lbs (18,000 kg)",
            "Turning Radius": "28.1 ft (9 m)",
            "Wheelbase": "181.2 in (460 cm)"
        },
        "Wheelbase Cab Chassis Option 5": {
            "Length from Back of Cab to End of Frame": "277.8 in (704 cm)",
            "Length From Back of Cab to End of Frame": "277.76 in (704 cm)",
            "Length From Center of Rear Axle(s) to End of Frame": "94.49 in (239 cm)",
            "Length from Center of Rear Axle(s) to End of Frame": "94.5 in (239 cm)",
            "Overall Length": "29.3 ft (9 m)",
            "Total Chassis Weight": "11508.2 lbs (5,220 kg)",
            "Total GVW": "39683.3 lbs (18,000 kg)",
            "Turning Radius": "30.1 ft (9 m)",
            "Wheelbase": "196.9 in (498 cm)"
        },
        "Wheelbase Cab Chassis Option 6": {
            "Length From Back of Cab to End of Frame": "312.6 in (792 cm)",
            "Length From Center of Rear Axle(s) to End of Frame": "105.71 in (267 cm)",
            "Length from Center of Rear Axle(s) to End of Frame": "105.8 in (267 cm)",
            "Overall Length": "32.2 ft (10 m)",
            "Total Chassis Weight": "11662.5 lbs (5,290 kg)",
            "Total GVW": "39683.3 lbs (18,000 kg)",
            "Turning Radius": "33 ft (10 m)",
            "Wheelbase": "220.5 in (559 cm)"
        },
        "Wheelbase Cab Chassis Option 7": {
            "Length From Back of Cab to End of Frame": "328.94 in (833 cm)",
            "Length from Back of Cab to End of Frame": "329 in (836 cm)",
            "Length From Center of Rear Axle(s) to End of Frame": "106.3 in (269 cm)",
            "Overall Length": "33.5 ft (10 m)",
            "Total Chassis Weight": "11684.5 lbs (5,300 kg)",
            "Total GVW": "39683.3 lbs (18,000 kg)",
            "Turning Radius": "35 ft (11 m)",
            "Wheelbase": "236.3 in (599 cm)"
        },
        "Wheelbase Cab Chassis Option 8": {
            "Length from Back of Cab to End of Frame": "366.4 in (930 cm)",
            "Length From Back of Cab to End of Frame": "366.34 in (930 cm)",
            "Length from Center of Rear Axle(s) to End of Frame": "124.1 in (315 cm)",
            "Length From Center of Rear Axle(s) to End of Frame": "124.02 in (315 cm)",
            "Overall Length": "36.6 ft (11 m)",
            "Total Chassis Weight": "11750.7 lbs (5,330 kg)",
            "Total GVW": "39683.3 lbs (18,000 kg)",
            "Turning Radius": "37.5 ft (11 m)",
            "Wheelbase": "256 in (650 cm)"
        }
    }
}