{
    "source_url": "https://www.constructionequipmentguide.com/charts/charts/truck-cranes/terex/tc-60l/30758489",
    "source_url_id": "30758489",
    "source_url_model": "tc-60l",
    "source_url_make": "terex",
    "source_url_category": "truck-cranes",
    "source_date_scraped": "2023-09-13 17:50:16.781208",
    "equipment_category": "Truck Cranes",
    "equipment_make": "Terex",
    "equipment_model": "TC 60L",
    "equipment_spec": {
        "Boom": {
            "Max Elevating Angle": "80  \t\u00b0",
            "Max Height @ Max Raise Angle - no jib": "144.4 ft (44 m)",
            "Max Lift Capacity": "132277.4 lbs (60,001 kg)",
            "Max Working Radius": "124.7 ft (38 m)",
            "Min Height @ Max Raise Angle": "32.5 ft (10 m)",
            "Min Working Radius": "8.3 ft (2 m)",
            "Number of Sections": "12",
            "Swing Speed": "1.8 rpm"
        },
        "CARRIER ENGINE": {
            "Make": "Terex",
            "Max Torque": "1327.7 lbs/ft",
            "Model": "D2066 LF33",
            "Net Power": "360 hp (268 kw)",
            "Power Measured @": "1900 rpm",
            "Torque Measured @": "1400 rpm"
        },
        "Dimensions": {
            "Carrier Length": "32.8 ft (10 m)",
            "Ground Clearance": "1.2 ft (0 m)",
            "Transport Height": "12.8 ft (4 m)",
            "Transport Length": "36.9 ft (11 m)",
            "Transport Width": "8.4 ft (2 m)",
            "Upper Structure Tail Swing Radius": "11.7 ft (3 m)",
            "Width w/ Outriggers Extended": "20.7 ft (6 m)"
        },
        "Operating Specifications": {
            "Carrier Fuel Capacity": "113.6 gal (428 l)",
            "Operating Voltage": "24 V V",
            "Operating Weight": "93035.1 lbs (42,200 kg)",
            "Tire Size": "385/65 R 22.5",
            "Upper Structure Hydraulic System Fluid Capacity": "154.6 gal (583 l)"
        },
        "Transmission": {
            "Max Speed - Forward": "56 mph (90 kph)",
            "Number of Forward Gears": "16",
            "Number of Reverse Gears": "2",
            "Transmission Type": "Manual gear box: ZF ECOSPLIT"
        }
    }
}