{
    "source_url": "https://www.constructionequipmentguide.com/charts/charts/excavators/komatsu/pc210lc-10-slf/30759911",
    "source_url_id": "30759911",
    "source_url_model": "pc210lc-10-slf",
    "source_url_make": "komatsu",
    "source_url_category": "excavators",
    "source_date_scraped": "2023-09-13 15:10:09.510336",
    "equipment_category": "Excavators",
    "equipment_make": "Komatsu",
    "equipment_model": "PC210LC-10 SLF",
    "equipment_spec": {
        "Boom/Stick Excavator Option 1": {
            "Max Digging Depth": "37.8 ft (11 m)",
            "Max Reach Along Ground": "49.7 ft (15 m)"
        },
        "Engine": {
            "Net Power": "158 hp (118 kw)"
        },
        "Operating Specifications": {
            "Operating Weight": "53368 lbs (24,208 kg)"
        }
    }
}