{
    "source_url": "https://www.constructionequipmentguide.com/charts/charts/compact-track-loaders/asv/rt-75/30760132",
    "source_url_id": "30760132",
    "source_url_model": "rt-75",
    "source_url_make": "asv",
    "source_url_category": "compact-track-loaders",
    "source_date_scraped": "2023-09-13 14:38:11.029648",
    "equipment_category": "Compact Track Loaders",
    "equipment_make": "ASV",
    "equipment_model": "RT-75",
    "equipment_spec": {
        "Engine": {
            "Gross Power": "74 hp (55 kw)"
        },
        "Loader": {
            "Operating Load Rating": "2650 lbs (1,202 kg)",
            "Operating Width": "70 in (178 cm)"
        }
    }
}