{
    "source_url": "https://www.constructionequipmentguide.com/charts/charts/excavators/komatsu/pc45mrx-1/30854360",
    "source_url_id": "30854360",
    "source_url_model": "pc45mrx-1",
    "source_url_make": "komatsu",
    "source_url_category": "excavators",
    "source_date_scraped": "2023-09-13 15:12:01.963013",
    "equipment_category": "Excavators",
    "equipment_make": "Komatsu",
    "equipment_model": "PC45MRx-1",
    "equipment_spec": {
        "Dimensions": {
            "Digging Depth": "11 ft (3 m)",
            "Digging Reach": "11 ft (3 m)"
        },
        "Engine": {
            "Net Power": "39 hp (29 kw)"
        },
        "Operating Specifications": {
            "Operating Weight": "10300 lbs (4,672 kg)"
        }
    }
}