{
    "source_url": "https://www.constructionequipmentguide.com/charts/charts/tractors/john-deere/850/31075013",
    "source_url_id": "31075013",
    "source_url_model": "850",
    "source_url_make": "john-deere",
    "source_url_category": "tractors",
    "source_date_scraped": "2023-09-13 17:24:41.136885",
    "equipment_category": "Tractors",
    "equipment_make": "John Deere",
    "equipment_model": "850",
    "equipment_spec": {
        "Engine": {
            "Gross Power": "25 hp (19 kw)"
        }
    }
}