{
    "source_url": "https://www.constructionequipmentguide.com/charts/charts/aerial-lifts/mec/1532es/47461",
    "source_url_id": "47461",
    "source_url_model": "1532es",
    "source_url_make": "mec",
    "source_url_category": "aerial-lifts",
    "source_date_scraped": "2023-09-13 14:30:41.787275",
    "equipment_category": "Aerial Lifts",
    "equipment_make": "Mec",
    "equipment_model": "1532ES",
    "equipment_spec": {
        "Dimensions": {
            "Ground Clearance": "3 in (8 cm)",
            "Height w/ Rails": "6.3 ft (2 m)",
            "Overall Length": "6.1 in (15 cm)",
            "Overall Width": "2.7 ft (1 m)",
            "Turning Radius": "6 ft (2 m)",
            "Wheelbase": "4.2 ft (1 m)"
        },
        "Engine": {
            "Battery Amp Hours": "220",
            "Charger Amps": "25",
            "Number of Batteries": "4",
            "System Voltage": "24 V"
        },
        "Performance": {
            "Hydraulic System Fluid Capacity": "3 gal (11 l)",
            "Max Speed": "3 mph (5 kph)",
            "Operating Weight": "2700 lbs (1,225 kg)",
            "Tire Fill/Type": "Solid, non-marking",
            "Tire Size": "14x4.5"
        },
        "Platform": {
            "Deck Extension": "35.9 in (89 cm)",
            "Height of Rails": "3.4 ft (1 m)",
            "Max Platform Height": "15 ft (5 m)",
            "Max Platform Weight Capacity": "600.1 lbs (272 kg)",
            "Max Working Height": "21.6 ft (6 m)",
            "Platform Inner Length": "66.2 in (168 cm)"
        }
    }
}