{
    "source_url": "https://www.constructionequipmentguide.com/charts/charts/wheel-loaders/doosan/dl550-5/47857",
    "source_url_id": "47857",
    "source_url_model": "dl550-5",
    "source_url_make": "doosan",
    "source_url_category": "wheel-loaders",
    "source_date_scraped": "2023-09-13 16:45:01.926324",
    "equipment_category": "Wheel Loaders",
    "equipment_make": "Doosan",
    "equipment_model": "DL550-5",
    "equipment_spec": {
        "Bucket": {
            "Breakout Force": "55303 lbs (25,085 kg)",
            "Bucket Capacity - heaped": "7.5 cu yds (5 m)",
            "Bucket Width": "11.2 ft (3 m)",
            "Dump Clearance at Max Raise": "11.2 ft (3 m)"
        },
        "Capacities": {
            "Cooling system": "16 gal (61 l)",
            "Diesel exhaust fluid (DEF) tank": "16 gal (61 l)",
            "Engine Oil": "12 gal (45 l)",
            "Fuel Tank": "117 gal (443 l)",
            "Hydraulic system": "65 gal (246 l)",
            "Transmission": "14 gal (53 l)"
        },
        "Dimensions": {
            "Digging depth": "3.2 in (8 cm)",
            "Ground Clearance": "1.6 ft (0 m)",
            "Hinge Pin - Max Height": "15.8 ft (5 m)",
            "Overall height": "12.5 ft in (30 cm)",
            "Overall length": "31.8 ft (9 m)",
            "Reach at Max Lift and Dump": "4.2 ft (1 m)",
            "Wheelbase": "12.2 ft (4 m)",
            "Width Over Tires": "14.7 ft (4 m)"
        },
        "Engine": {
            "Alternator": "100 A",
            "Bore": "5.2 in (13 cm)",
            "Displacement": "775.1 cu in (0 m)",
            "Engine Make": "Scania",
            "Engine Model": "DC13",
            "Gross Power": "380 hp (283 kw)",
            "Horsepower -Net": "271 hp (202 kw)",
            "Make": "Scania",
            "Net Power": "380 hp (283 kw)",
            "Net Torque": "1121.1 lbs/ft",
            "Number of Cylinders": "6",
            "Power Measured @": "1800 rpm",
            "Starter": "8 hp (6 kw)",
            "Stroke": "6.3 in (15 cm)",
            "Torque Measured @": "1400 rpm"
        },
        "Hydraulic System": {
            "Dump Time": "1.4 sec",
            "Lower Time": "4.2 sec",
            "Raise Time": "6.4 sec",
            "Relief Valve Pressure": "3989 psi"
        },
        "Operating Specifications": {
            "Front Axle/Diff Fluid Capacity": "16.5 gal (61 l)",
            "Operating Voltage": "28 V V",
            "Operating Weight": "69897.6 lbs (31,705 kg)",
            "Rated Bucket Capacity": "7.5 cu yds (5 m)",
            "Rear Axle/Diff Fluid Capacity": "16.9 gal (61 l)",
            "Static Tipping Weight": "53175.5 lbs (24,120 kg)",
            "Tire Size": "29.5-25"
        },
        "Transmission": {
            "Max Speed - Forward": "22.4 mph (35 kph)",
            "Max Speed - Reverse": "16.1 mph (26 kph)"
        },
        "Weights": {
            "Operational Weight": "69909 lbs (31,711 kg)"
        }
    }
}