{
    "source_url": "https://www.constructionequipmentguide.com/charts/charts/motor-graders/caterpillar/143h/6529",
    "source_url_id": "6529",
    "source_url_model": "143h",
    "source_url_make": "caterpillar",
    "source_url_category": "motor-graders",
    "source_date_scraped": "2023-09-13 16:20:22.732105",
    "equipment_category": "Motor Graders",
    "equipment_make": "Caterpillar",
    "equipment_model": "143H",
    "equipment_spec": {
        "Circle": {
            "Blade Tip Angle - Front": "40  \t\u00b0",
            "Blade Tip Angle - Rear": "5  \t\u00b0",
            "Diameter": "60.2 in (152 cm)",
            "Max Lift Above Ground": "18.9 in (46 cm)",
            "Max Reach Outside Tires - Left": "74.6 in (188 cm)",
            "Max Reach Outside Tires - Right": "77.9 in (196 cm)",
            "Shift Left": "27.4 in (69 cm)",
            "Shift Right": "28.7 in (71 cm)"
        },
        "Dimensions": {
            "Blade Base": "8.4 ft (2 m)",
            "Front Ground Clearance": "2 ft (1 m)",
            "Height to Top of Isomount Cab": "10.3 ft (3 m)",
            "Overall Length": "28.6 ft (9 m)",
            "Rear Ground Clearance": "1.2 ft (0 m)",
            "Tandem Axle Wheelbase": "5 ft (2 m)",
            "Wheelbase": "20.3 ft (6 m)",
            "Width Over Tires": "8.4 ft (2 m)"
        },
        "Engine": {
            "Displacement": "629 cu in (0 m)",
            "Engine Model": "3176C DITA ATAAC VHP",
            "Max Power": "205 hp (153 kw)",
            "Net Power Gear 1-2": "165 hp (123 kw)",
            "Net Power Gear 4-6": "185 hp (138 kw)",
            "Net Power Gear 5-6": "185 hp (138 kw)",
            "Net Power Gears 7-8": "205 hp (153 kw)"
        },
        "Front Axle": {
            "Ground Clearance": "2 ft (1 m)",
            "Oscillation - Total": "32  \t\u00b0",
            "Wheel Lean": "18  \t\u00b0"
        },
        "Hydraulic System": {
            "Pump Flow": "54.4 gal/min (204 l/min)",
            "Pump Type": "axial piston",
            "Relief Valve Pressure": "3500 psi"
        },
        "Moldboard": {
            "Blade Down Pressure": "30126.2 lbs (13,665 kg)",
            "Blade Pull at Max Weight": "43977 lbs (19,948 kg)",
            "Max Depth of Cut": "28.1 in (71 cm)",
            "Moldboard Height": "24 in (61 cm)",
            "Moldboard Thickness": "0.9 in (0 cm)",
            "Moldboard Width": "12 ft (4 m)",
            "Side Shift Left": "20.6 in (51 cm)",
            "Side Shift Right": "26 in (66 cm)"
        },
        "Operating Specifications": {
            "Circle Gearbox Fluid Capacity": "1.8 gal (4 l)",
            "Cooling System Fluid Capacity": "10 gal (38 l)",
            "Fuel Capacity": "105 gal (397 l)",
            "Hydraulic System Fluid Capacity": "20.8 gal (76 l)",
            "Max Operation Weight - Front Axle": "17443 lbs (7,912 kg)",
            "Max Operation Weight - Rear Axle": "31420 lbs (14,252 kg)",
            "Max Operation Weight - Total": "48863 lbs (22,164 kg)",
            "Std Operation Weight - Front Axle": "9493 lbs (4,306 kg)",
            "Std Operation Weight - Rear Axle": "24177 lbs (10,967 kg)",
            "Std Operation Weight - Total": "33670 lbs (15,273 kg)",
            "Tandem Case Fluid Capacity (each)": "16.9 gal (61 l)"
        },
        "Steering System": {
            "Articulation Angle": "20  \t\u00b0",
            "Turning Radius": "24.6 ft (7 m)"
        },
        "Transmission": {
            "Max Speed - Forward": "27.4 mph (43 kph)",
            "Max Speed - Reverse": "21.6 mph (34 kph)",
            "Number of Gears - Forward": "8",
            "Number of Gears - Reverse": "6",
            "Transmission Type": "direct drive, power shift"
        }
    }
}