{
    "source_url": "https://www.constructionequipmentguide.com/charts/charts/wheel-loaders/liugong/zl50c/8629296",
    "source_url_id": "8629296",
    "source_url_model": "zl50c",
    "source_url_make": "liugong",
    "source_url_category": "wheel-loaders",
    "source_date_scraped": "2023-09-13 16:53:35.450976",
    "equipment_category": "Wheel Loaders",
    "equipment_make": "Liugong",
    "equipment_model": "ZL50C",
    "equipment_spec": {
        "Bucket": {
            "Breakout Force": "35969.5 lbs (16,315 kg)",
            "Bucket Capacity - heaped": "4 cu yds (3 m)",
            "Dump Clearance at Max Raise": "9.8 ft (3 m)"
        },
        "Dimensions": {
            "Height - Top of Cab": "11.5 ft (3 m)",
            "Length with Bucket on Ground": "26.4 ft (8 m)",
            "Reach at Max Lift and Dump": "4 ft (1 m)",
            "Width Over Tires": "9.8 ft (3 m)"
        },
        "Engine": {
            "Engine Model": "WD61567G3-36",
            "Net Power": "217.3 hp (162 kw)",
            "Power Measured @": "2200 rpm"
        },
        "Hydraulic System": {
            "Pump Type": "Gear"
        },
        "Operating Specifications": {
            "Operating Weight": "36376.3 lbs (16,500 kg)",
            "Tire Size": "23.5-25"
        },
        "Transmission": {
            "Max Speed - Forward": "21.2 mph (34 kph)",
            "Max Speed - Reverse": "8.1 mph (13 kph)",
            "Number of Forward Gears": "2",
            "Number of Reverse Gears": "1",
            "Transmission Type": "Powershift"
        }
    }
}